README.rst
setup.py
jaml/__init__.py
microyaml.egg-info/PKG-INFO
microyaml.egg-info/SOURCES.txt
microyaml.egg-info/dependency_links.txt
microyaml.egg-info/top_level.txt